redis_tasks/__init__.py
redis_tasks/cli.py
redis_tasks/conf.py
redis_tasks/defaults.py
redis_tasks/exceptions.py
redis_tasks/queue.py
redis_tasks/registries.py
redis_tasks/scheduler.py
redis_tasks/smear_dst.py
redis_tasks/task.py
redis_tasks/utils.py
redis_tasks/worker.py
redis_tasks/worker_process.py
redis_tasks/contrib/__init__.py
redis_tasks/contrib/graph.py
redis_tasks/contrib/sentry.py
redis_tasks/contrib/django/__init__.py
redis_tasks/contrib/django/management/__init__.py
redis_tasks/contrib/django/management/commands/__init__.py
redis_tasks/contrib/django/management/commands/redis_tasks.py
tests/__init__.py
tests/conftest.py
tests/test_cli.py
tests/test_conf.py
tests/test_maintenance.py
tests/test_queue.py
tests/test_registries.py
tests/test_scheduler.py
tests/test_smear_dst.py
tests/test_task.py
tests/test_task_execution.py
tests/test_utils.py
tests/test_worker.py
tests/test_workerprocess.py
tests/test_workhorse.py
tests/utils.py
tests/app/__init__.py
tests/app/import_me.py
tests/app/settings.py
tests/app/settings_a.py
tests/contrib/__init__.py
tests/contrib/test_graph.py
redis_tasks-0.0.11.dist-info/LICENSE
redis_tasks-0.0.11.dist-info/METADATA
redis_tasks-0.0.11.dist-info/WHEEL
redis_tasks-0.0.11.dist-info/entry_points.txt
redis_tasks-0.0.11.dist-info/top_level.txt
redis_tasks-0.0.11.dist-info/RECORD
