Metadata-Version: 2.1
Name: redis-tasks
Version: 0.0.11
Summary: redis-tasks is a lightweight library for processing background tasks
Home-page: https://github.com/djangsters/redis-tasks/
Author: Christian Fersch
Author-email: christian@djangsters.de
License: UNKNOWN
Platform: any
Classifier: Development Status :: 3 - Alpha
Classifier: License :: OSI Approved :: BSD License
Classifier: Operating System :: POSIX
Classifier: Programming Language :: Python :: 3
Classifier: Programming Language :: Python :: 3.7
Classifier: Programming Language :: Python :: 3.8
Classifier: Programming Language :: Python :: 3.9
Requires-Python: >=3.7
License-File: LICENSE
Requires-Dist: redis (>=3.2.0)
Requires-Dist: click
Requires-Dist: croniter (>=0.3.23)
Requires-Dist: pytz
